facebookrequests/__init__.py
facebookrequests/facebookrequests.py
tests/__init__.py
tests/test_facebookrequests.py
facebookrequests-0.0.1.dist-info/METADATA
facebookrequests-0.0.1.dist-info/WHEEL
facebookrequests-0.0.1.dist-info/top_level.txt
facebookrequests-0.0.1.dist-info/RECORD
