Metadata-Version: 2.1
Name: facebookrequests
Version: 0.0.1
Summary: A Python package for handling API interactions with Facebook, utilizing the Python requests package.
Home-page: https://your.package.url
Author: Dan Norwood
Author-email: norwood.dan@gmail.com
Classifier: Development Status :: 2 - Pre-Alpha
Classifier: Intended Audience :: Developers
Classifier: Natural Language :: English
Classifier: License :: OSI Approved :: MIT License
Classifier: Programming Language :: Python :: 3
Classifier: Programming Language :: Python :: 3.11
Requires-Python: >=3.11
Requires-Dist: requests
Requires-Dist: Pillow
